mara_cron/__init__.py
mara_cron/cli.py
mara_cron/config.py
mara_cron/crontab.py
mara_cron/job.py
mara_cron/views.py
mara_cron/ui/__init__.py
mara_cron/ui/schedule_run.py
mara_cron-0.12.0.dist-info/LICENSE
mara_cron-0.12.0.dist-info/METADATA
mara_cron-0.12.0.dist-info/WHEEL
mara_cron-0.12.0.dist-info/entry_points.txt
mara_cron-0.12.0.dist-info/top_level.txt
mara_cron-0.12.0.dist-info/RECORD
