Metadata-Version: 2.1
Name: mara-cron
Version: 0.12.0
Summary: Lets you manage cron jobs via mara
Home-page: https://github.com/mara/mara-cron
Author: Mara contributors
License: MIT
Requires-Python: >=3.7
License-File: LICENSE
Requires-Dist: mara-page >=1.5.2
Requires-Dist: python-crontab >=2.5.1
Requires-Dist: click >=7.1.2
Requires-Dist: mara-cli >=0.3.1
Provides-Extra: test
Requires-Dist: pytest ; extra == 'test'
Requires-Dist: mara-app >=2.2.0 ; extra == 'test'
